flask_occam/__init__.py
flask_occam/converters.py
flask_occam/decorators.py
flask_occam/errors.py
flask_occam/handlers.py
flask_occam/mixins.py
flask_occam/plugin.py
Flask_Occam-0.2.1.dist-info/LICENSE
Flask_Occam-0.2.1.dist-info/METADATA
Flask_Occam-0.2.1.dist-info/WHEEL
Flask_Occam-0.2.1.dist-info/top_level.txt
Flask_Occam-0.2.1.dist-info/RECORD
