Metadata-Version: 2.1
Name: Flask-Occam
Version: 0.2.1
Summary: Flask extension for simplifying REST API development.
Home-page: https://github.com/bprinty/Flask-Occam
Author: Blake Printy
Author-email: bprinty@gmail.com
License: MIT
Keywords: Flask-Occam,flask,rest,web,validation
Platform: any
Classifier: Environment :: Web Environment
Classifier: Intended Audience :: Developers
Classifier: License :: OSI Approved :: MIT License
Classifier: Operating System :: OS Independent
Classifier: Programming Language :: Python
Classifier: Topic :: Internet :: WWW/HTTP :: Dynamic Content
Classifier: Topic :: Software Development :: Libraries :: Python Modules
Classifier: Natural Language :: English
Classifier: Programming Language :: Python :: 2
Classifier: Programming Language :: Python :: 2.6
Classifier: Programming Language :: Python :: 2.7
Classifier: Programming Language :: Python :: 3
Classifier: Programming Language :: Python :: 3.3
Classifier: Programming Language :: Python :: 3.4
Classifier: Programming Language :: Python :: 3.5
Classifier: Programming Language :: Python :: 3.6
Classifier: Programming Language :: Python :: 3.7
Requires-Dist: Flask
Requires-Dist: WTForms
Requires-Dist: PyYAML
Requires-Dist: six
